{
    "config": [
        5,
        5,
        1
    ],
    "adjMatrix": [
        [
            null,
            null,
            null,
            null,
            null,
            0.5174082287984247,
            0.23952061908624386,
            1.179989068914451,
            0.4894244000294242,
            -1.6689562843389658,
            null
        ],
        [
            null,
            null,
            null,
            null,
            null,
            -0.34643577583017116,
            -3.2489522456044067,
            1.0248932128350396,
            -0.5573030230822952,
            0.156540444059374,
            null
        ],
        [
            null,
            null,
            null,
            null,
            null,
            0.36323729293579216,
            -0.23846961756375648,
            -1.009769434991739,
            1.7083079228671079,
            -3.2481021070028073,
            null
        ],
        [
            null,
            null,
            null,
            null,
            null,
            0.08835342065459302,
            0.7718935261617509,
            0.3335085218436258,
            0.06705290493374207,
            -0.24261456572083565,
            null
        ],
        [
            null,
            null,
            null,
            null,
            null,
            -1.073054210816751,
            -1.7273660173522731,
            -2.2124038964646795,
            -2.762384871696248,
            1.7869975940252767,
            null
        ],
        [
            null,
            null,
            null,
            null,
            null,
            0.44365776724563816,
            null,
            null,
            null,
            null,
            1.5111422865525714
        ],
        [
            null,
            null,
            null,
            null,
            null,
            null,
            1.3756614961535147,
            null,
            null,
            null,
            -2.36092833182721
        ],
        [
            null,
            null,
            null,
            null,
            null,
            null,
            null,
            -1.2363497031962265,
            null,
            null,
            2.816542291158966
        ],
        [
            null,
            null,
            null,
            null,
            null,
            null,
            null,
            null,
            2.342113062114402,
            null,
            3.6405604918353704
        ],
        [
            null,
            null,
            null,
            null,
            null,
            null,
            null,
            null,
            null,
            3.6520809516511243,
            -4.194138707383064
        ],
        [
            null,
            null,
            null,
            null,
            null,
            null,
            null,
            null,
            null,
            null,
            -0.05757434496832555
        ]
    ],
    "useLinearInOutput": false,
    "useTanh": false,
    "epochs": 12288,
    "useMomentum": false,
    "useBoldDriver": false,
    "useWeightDecay": false,
    "useAnnealing": false,
    "useBatchLearning": false,
    "RMSE": 0.02015209649613559
}